fifteen_puzzle_solvers/__init__.py
fifteen_puzzle_solvers/main.py
fifteen_puzzle_solvers/domain/__init__.py
fifteen_puzzle_solvers/domain/puzzle.py
fifteen_puzzle_solvers/services/__init__.py
fifteen_puzzle_solvers/services/solver.py
fifteen_puzzle_solvers/services/algorithms/__init__.py
fifteen_puzzle_solvers/services/algorithms/astar.py
fifteen_puzzle_solvers/services/algorithms/base.py
fifteen_puzzle_solvers/services/algorithms/breadth_first.py
fifteen_puzzle_solvers/services/puzzle/__init__.py
fifteen_puzzle_solvers/services/puzzle/constants.py
fifteen_puzzle_solvers/services/puzzle/heuristic.py
fifteen_puzzle_solvers/services/puzzle/shuffle.py
fifteen_puzzle_solvers/services/puzzle/validation.py
fifteen_puzzle_solvers/ui/__init__.py
fifteen_puzzle_solvers/ui/puzzle_game.py
fifteen_puzzle_solvers-2.0.3.dist-info/LICENSE
fifteen_puzzle_solvers-2.0.3.dist-info/METADATA
fifteen_puzzle_solvers-2.0.3.dist-info/WHEEL
fifteen_puzzle_solvers-2.0.3.dist-info/top_level.txt
fifteen_puzzle_solvers-2.0.3.dist-info/RECORD
