Metadata-Version: 2.1
Name: fifteen_puzzle_solvers
Version: 2.0.3
Summary: Different solvers for the 15 puzzle sliding game
Home-page: https://github.com/MilanPecov/15-Puzzle-Solvers
Author: Milan Pecov
Author-email: mpecov@yahoo.ca
Keywords: 15-puzzle sliding-game algorithms A* breadth-first search heuristics python path-finding
Classifier: Programming Language :: Python :: 3
Classifier: License :: OSI Approved :: MIT License
Classifier: Operating System :: OS Independent
Classifier: Intended Audience :: Developers
Classifier: Intended Audience :: Science/Research
Classifier: Intended Audience :: Education
Classifier: Intended Audience :: End Users/Desktop
Classifier: Topic :: Games/Entertainment :: Puzzle Games
Classifier: Topic :: Scientific/Engineering :: Artificial Intelligence
Classifier: Topic :: Software Development :: Libraries :: Python Modules
Requires-Python: >=3.6
License-File: LICENSE
